{"cameraMode":{"drawMode":0,"name":"Shaded","section":"Shading Mode"},"sceneLighting":false,"audioPlay":false,"sceneViewState":{"m_AlwaysRefresh":false,"showFog":true,"showSkybox":false,"showFlares":true,"showImageEffects":true,"showParticleSystems":true,"showVisualEffectGraphs":true,"m_FxEnabled":true},"in2DMode":false,"pivot":{"x":-1055.789306640625,"y":157.25987243652345,"z":995.0},"rotation":{"x":0.20846030116081239,"y":-0.0020370399579405786,"z":0.000435290508903563,"w":0.9780305624008179},"size":161.7099151611328,"orthographic":false}